chitchatcli/__init__.py
chitchatcli/__main__.py
chitchatcli/globalvaribles.py
chitchatcli/utilis/__init__.py
chitchatcli/utilis/apicalls.py
chitchatcli/utilis/event.py
chitchatcli/utilis/helper_functions.py
chitchatcli/utilis/process.py
chitchatcli/utilis/screen_functions.py
chitchatcli/utilis/storage.py
chitchatcli-0.0.3.dist-info/LICENSE.txt
chitchatcli-0.0.3.dist-info/METADATA
chitchatcli-0.0.3.dist-info/WHEEL
chitchatcli-0.0.3.dist-info/top_level.txt
chitchatcli-0.0.3.dist-info/RECORD
