Metadata-Version: 2.1
Name: chitchatcli
Version: 0.0.3
Summary: A command line chatting software designed for developers to communicate with each other.
Author: Benjamin Eruvieru
Author-email: benjamineruvieru@gmail.com
Classifier: Programming Language :: Python :: 3
Classifier: License :: OSI Approved :: MIT License
Classifier: Operating System :: OS Independent
License-File: LICENSE.txt
Requires-Dist: python-socketio[client]
Requires-Dist: windows-curses (==2.3.1) ; sys_platform == "win32"
